{
  "updated": "2026-04-13T11:53:45+09:00",
  "team_a": "BNK 썸",
  "team_b": "하나은행",
  "season_h2h": {
    "하나은행": "5승 1패",
    "BNK 썸": "1승 5패"
  },
  "all_time_h2h": {
    "하나은행": "19승 22패",
    "BNK 썸": "22승 19패"
  },
  "games": [
    {
      "date": "2025-12-01",
      "venue": "부천체육관",
      "time": "19:00",
      "mvp": "진안(하나은행)",
      "game_no": "14"
    },
    {
      "date": "2025-12-17",
      "venue": "부산사직실내체육관",
      "time": "19:00",
      "mvp": "진안(하나은행)",
      "game_no": "27"
    },
    {
      "date": "2026-01-14",
      "venue": "부산사직실내체육관",
      "time": "19:00",
      "mvp": "진안(하나은행)",
      "game_no": "44"
    },
    {
      "date": "2026-01-30",
      "venue": "부천체육관",
      "time": "19:00",
      "mvp": "박혜진(BNK 썸)",
      "game_no": "57"
    },
    {
      "date": "2026-02-07",
      "venue": "부산사직실내체육관",
      "time": "14:00",
      "mvp": "이이지마 사키(하나은행)",
      "game_no": "64"
    },
    {
      "date": "2026-03-28",
      "venue": "부천체육관",
      "time": "14:00",
      "mvp": "박혜진(BNK 썸)",
      "game_no": "85"
    }
  ]
}